{
  "$schema": "https://ui.shadcn.com/schema/registry-item.json",
  "name": "dialog-header",
  "title": "Dialog Header",
  "description": "Reactolith wrapper for shadcn DialogHeader.",
  "registryDependencies": [
    "dialog"
  ],
  "files": [
    {
      "path": "registry/new-york/reactolith/dialog/dialog-header.tsx",
      "content": "import { DialogHeader } from \"@/components/ui/dialog\"\nexport default DialogHeader\n",
      "type": "registry:file",
      "target": "components/reactolith/dialog/dialog-header.tsx"
    }
  ],
  "type": "registry:component"
}